{
    "paths": [
        {
            "name": "/coins",
            "lambdaFunction": "cryptofunction",
            "privacy": {
                "open": true
            },
            "policyResourceName": "/coins"
        }
    ],
    "resourceName": "criptoapi",
    "apiName": "criptoapi",
    "functionArns": [
        {
            "lambdaFunction": "cryptofunction"
        }
    ],
    "privacy": {
        "auth": 0,
        "unauth": 0,
        "authRoleName": "amplify-amplifyapp-dev-214500-authRole",
        "unAuthRoleName": "amplify-amplifyapp-dev-214500-unauthRole"
    },
    "dependsOn": [
        {
            "category": "function",
            "resourceName": "cryptofunction",
            "attributes": [
                "Name",
                "Arn"
            ]
        }
    ]
}